[{"id": 34429415, "bathrooms": 1.0, "bedrooms": 2, "beds": 4, "disc_m": 0.55, "disc_w": 0.88, "coordinates": {"lat": 49.98112, "lng": 14.52567}}, {"id": 26359954, "bathrooms": 2.0, "bedrooms": 4, "beds": 5, "disc_m": 0.7, "disc_w": 0.9, "coordinates": {"lat": 50.028, "lng": 14.50463}}, {"id": 12117258, "bathrooms": 1.0, "bedrooms": 0, "beds": 1, "disc_m": 1.0, "disc_w": 1.0, "coordinates": {"lat": 50.01403, "lng": 14.51231}}, {"id": 26596148, "bathrooms": 1.0, "bedrooms": 1, "beds": 2, "disc_m": 0.79, "disc_w": 0.95, "coordinates": {"lat": 50.036125, "lng": 14.485312}}, {"id": 12194720, "bathrooms": 1.0, "bedrooms": 0, "beds": 1, "disc_m": 1.0, "disc_w": 1.0, "coordinates": {"lat": 50.01415, "lng": 14.51378}}, {"id": 20129557, "bathrooms": 1.0, "bedrooms": 1, "beds": 3, "disc_m": 0.6, "disc_w": 0.82, "coordinates": {"lat": 50.03715, "lng": 14.48303}}, {"id": 33638279, "bathrooms": 1.0, "bedrooms": 2, "beds": 3, "disc_m": 1.0, "disc_w": 1.0, "coordinates": {"lat": 50.04249, "lng": 14.47614}}, {"id": 37440737, "bathrooms": 11.0, "bedrooms": 5, "beds": 3, "disc_m": 0.65, "disc_w": 0.8, "coordinates": {"lat": 49.96777, "lng": 14.51272}}, {"id": 25240790, "bathrooms": 2.5, "bedrooms": 2, "beds": 2, "disc_m": 0.75, "disc_w": 0.83, "coordinates": {"lat": 50.03252, "lng": 14.50134}}, {"id": 25491795, "bathrooms": 1.0, "bedrooms": 0, "beds": 4, "disc_m": 1.0, "disc_w": 1.0, "coordinates": {"lat": 50.03601, "lng": 14.48287}}, {"id": 9470517, "bathrooms": 1.0, "bedrooms": 1, "beds": 1, "disc_m": 1.0, "disc_w": 1.0, "coordinates": {"lat": 50.03958, "lng": 14.55675}}, {"id": 21842050, "bathrooms": 1.0, "bedrooms": 1, "beds": 1, "disc_m": 1.0, "disc_w": 1.0, "coordinates": {"lat": 50.03828, "lng": 14.55533}}, {"id": 23844907, "bathrooms": 1.5, "bedrooms": 1, "beds": 2, "disc_m": 1.0, "disc_w": 1.0, "coordinates": {"lat": 49.99025, "lng": 14.47266}}, {"id": 31857024, "bathrooms": 1.5, "bedrooms": 1, "beds": 1, "disc_m": 1.0, "disc_w": 1.0, "coordinates": {"lat": 50.0432, "lng": 14.50265}}, {"id": 30330698, "bathrooms": 1.5, "bedrooms": 2, "beds": 3, "disc_m": 1.0, "disc_w": 1.0, "coordinates": {"lat": 50.04379, "lng": 14.55084}}, {"id": 17713207, "bathrooms": 2.0, "bedrooms": 1, "beds": 2, "disc_m": 0.75, "disc_w": 0.9, "coordinates": {"lat": 50.043037, "lng": 14.501606}}, {"id": 23254731, "bathrooms": 1.0, "bedrooms": 1, "beds": 2, "disc_m": 1.0, "disc_w": 0.82, "coordinates": {"lat": 49.99053, "lng": 14.47294}}, {"id": 7429318, "bathrooms": 1.5, "bedrooms": 1, "beds": 4, "disc_m": 1.0, "disc_w": 1.0, "coordinates": {"lat": 50.03568, "lng": 14.48672}}, {"id": 22711946, "bathrooms": 3.5, "bedrooms": 4, "beds": 8, "disc_m": 1.0, "disc_w": 1.0, "coordinates": {"lat": 49.99243, "lng": 14.48203}}, {"id": 23844797, "bathrooms": 1.0, "bedrooms": 2, "beds": 4, "disc_m": 1.0, "disc_w": 1.0, "coordinates": {"lat": 49.99091, "lng": 14.47377}}, {"id": 12197489, "bathrooms": 1.0, "bedrooms": 0, "beds": 2, "disc_m": 1.0, "disc_w": 1.0, "coordinates": {"lat": 50.01406, "lng": 14.51258}}, {"id": 12197675, "bathrooms": 1.0, "bedrooms": 0, "beds": 3, "disc_m": 1.0, "disc_w": 1.0, "coordinates": {"lat": 50.01397, "lng": 14.5146}}, {"id": 12307529, "bathrooms": 1.5, "bedrooms": 2, "beds": 1, "disc_m": 1.0, "disc_w": 1.0, "coordinates": {"lat": 50.02046, "lng": 14.48401}}, {"id": 7139480, "bathrooms": 1.0, "bedrooms": 1, "beds": 1, "disc_m": 0.8, "disc_w": 0.9, "coordinates": {"lat": 50.02701, "lng": 14.48988}}, {"id": 10538644, "bathrooms": 1.0, "bedrooms": 3, "beds": 7, "disc_m": 0.75, "disc_w": 0.8, "coordinates": {"lat": 50.03797, "lng": 14.48135}}, {"id": 35355750, "bathrooms": 1.5, "bedrooms": 3, "beds": 3, "disc_m": 0.8, "disc_w": 0.9, "coordinates": {"lat": 50.02061, "lng": 14.48626}}, {"id": 16280145, "bathrooms": 1.0, "bedrooms": 3, "beds": 3, "disc_m": 0.9, "disc_w": 1.0, "coordinates": {"lat": 49.99762, "lng": 14.5225}}, {"id": 22318049, "bathrooms": 1.0, "bedrooms": 3, "beds": 6, "disc_m": 0.8, "disc_w": 0.9, "coordinates": {"lat": 49.97277, "lng": 14.51013}}, {"id": 12803768, "bathrooms": 1.0, "bedrooms": 2, "beds": 4, "disc_m": 1.0, "disc_w": 0.9, "coordinates": {"lat": 50.04078, "lng": 14.47947}}, {"id": 31033290, "bathrooms": 1.0, "bedrooms": 1, "beds": 1, "disc_m": 1.0, "disc_w": 1.0, "coordinates": {"lat": 50.03314, "lng": 14.48293}}, {"id": 29005569, "bathrooms": 1.0, "bedrooms": 2, "beds": 2, "disc_m": 1.0, "disc_w": 0.93, "coordinates": {"lat": 50.04104, "lng": 14.49708}}, {"id": 18325770, "bathrooms": 1.0, "bedrooms": 1, "beds": 2, "disc_m": 0.8, "disc_w": 0.9, "coordinates": {"lat": 50.10575, "lng": 14.47429}}, {"id": 35700877, "bathrooms": 1.0, "bedrooms": 1, "beds": 1, "disc_m": 1.0, "disc_w": 1.0, "coordinates": {"lat": 50.09756, "lng": 14.46494}}, {"id": 16564853, "bathrooms": 1.0, "bedrooms": 2, "beds": 2, "disc_m": 0.8, "disc_w": 0.9, "coordinates": {"lat": 50.09809, "lng": 14.46785}}, {"id": 7268802, "bathrooms": 1.0, "bedrooms": 0, "beds": 2, "disc_m": 1.0, "disc_w": 1.0, "coordinates": {"lat": 50.10325, "lng": 14.47485}}, {"id": 13248278, "bathrooms": 1.0, "bedrooms": 0, "beds": 1, "disc_m": 1.0, "disc_w": 1.0, "coordinates": {"lat": 50.097202, "lng": 14.465509}}, {"id": 30933192, "bathrooms": 1.0, "bedrooms": 0, "beds": 1, "disc_m": 0.95, "disc_w": 0.98, "coordinates": {"lat": 50.097328, "lng": 14.466361}}, {"id": 30788176, "bathrooms": 1.0, "bedrooms": 1, "beds": 1, "disc_m": 0.95, "disc_w": 0.98, "coordinates": {"lat": 50.097328, "lng": 14.466361}}, {"id": 5974283, "bathrooms": 1.0, "bedrooms": 1, "beds": 1, "disc_m": 0.87, "disc_w": 0.9, "coordinates": {"lat": 50.09405, "lng": 14.46407}}, {"id": 12884543, "bathrooms": 1.0, "bedrooms": 0, "beds": 2, "disc_m": 0.9, "disc_w": 0.95, "coordinates": {"lat": 50.10692, "lng": 14.46992}}, {"id": 13584766, "bathrooms": 1.5, "bedrooms": 1, "beds": 3, "disc_m": 1.0, "disc_w": 0.9, "coordinates": {"lat": 50.10485, "lng": 14.47388}}, {"id": 24341316, "bathrooms": 1.0, "bedrooms": 0, "beds": 1, "disc_m": 0.9, "disc_w": 0.95, "coordinates": {"lat": 50.09359, "lng": 14.46371}}, {"id": 30464396, "bathrooms": 1.0, "bedrooms": 0, "beds": 1, "disc_m": 1.0, "disc_w": 1.0, "coordinates": {"lat": 50.098, "lng": 14.46615}}, {"id": 12101937, "bathrooms": 1.0, "bedrooms": 1, "beds": 2, "disc_m": 0.85, "disc_w": 1.0, "coordinates": {"lat": 50.10045, "lng": 14.47019}}, {"id": 9839921, "bathrooms": 1.0, "bedrooms": 1, "beds": 4, "disc_m": 1.0, "disc_w": 0.93, "coordinates": {"lat": 50.09716, "lng": 14.46419}}, {"id": 26831300, "bathrooms": 1.0, "bedrooms": 0, "beds": 2, "disc_m": 1.0, "disc_w": 0.86, "coordinates": {"lat": 50.096802, "lng": 14.465157}}, {"id": 24254613, "bathrooms": 1.0, "bedrooms": 1, "beds": 3, "disc_m": 0.8, "disc_w": 0.9, "coordinates": {"lat": 50.095524, "lng": 14.467073}}, {"id": 23188088, "bathrooms": 1.0, "bedrooms": 0, "beds": 1, "disc_m": 0.9, "disc_w": 0.95, "coordinates": {"lat": 50.09733, "lng": 14.46586}}, {"id": 20980479, "bathrooms": 1.0, "bedrooms": 1, "beds": 1, "disc_m": 0.8, "disc_w": 0.95, "coordinates": {"lat": 50.09734, "lng": 14.46455}}, {"id": 20602252, "bathrooms": 1.0, "bedrooms": 1, "beds": 1, "disc_m": 1.0, "disc_w": 1.0, "coordinates": {"lat": 50.09581, "lng": 14.47197}}, {"id": 32198858, "bathrooms": 1.0, "bedrooms": 2, "beds": 4, "disc_m": 0.9, "disc_w": 0.95, "coordinates": {"lat": 50.09643, "lng": 14.46464}}, {"id": 13386515, "bathrooms": 1.0, "bedrooms": 1, "beds": 3, "disc_m": 0.7, "disc_w": 0.85, "coordinates": {"lat": 50.10675, "lng": 14.46561}}, {"id": 28224340, "bathrooms": 1.0, "bedrooms": 0, "beds": 2, "disc_m": 1.0, "disc_w": 1.0, "coordinates": {"lat": 50.09733, "lng": 14.46279}}, {"id": 14242408, "bathrooms": 1.0, "bedrooms": 1, "beds": 2, "disc_m": 1.0, "disc_w": 0.95, "coordinates": {"lat": 50.09785, "lng": 14.4671}}, {"id": 33095713, "bathrooms": 1.0, "bedrooms": 1, "beds": 2, "disc_m": 1.0, "disc_w": 1.0, "coordinates": {"lat": 50.09623, "lng": 14.46324}}, {"id": 26680456, "bathrooms": 1.0, "bedrooms": 2, "beds": 3, "disc_m": 0.9, "disc_w": 0.95, "coordinates": {"lat": 50.09709, "lng": 14.46403}}, {"id": 15255060, "bathrooms": 1.0, "bedrooms": 1, "beds": 1, "disc_m": 1.0, "disc_w": 1.0, "coordinates": {"lat": 50.10676, "lng": 14.4708}}, {"id": 17628786, "bathrooms": 1.0, "bedrooms": 2, "beds": 4, "disc_m": 0.9, "disc_w": 1.0, "coordinates": {"lat": 50.09669, "lng": 14.46637}}, {"id": 30751914, "bathrooms": 1.0, "bedrooms": 1, "beds": 1, "disc_m": 1.0, "disc_w": 1.0, "coordinates": {"lat": 50.096912, "lng": 14.465235}}, {"id": 32016130, "bathrooms": 2.5, "bedrooms": 2, "beds": 3, "disc_m": 0.95, "disc_w": 0.98, "coordinates": {"lat": 50.097328, "lng": 14.466361}}, {"id": 14897770, "bathrooms": 1.0, "bedrooms": 0, "beds": 1, "disc_m": 0.85, "disc_w": 0.95, "coordinates": {"lat": 50.095097, "lng": 14.464189}}, {"id": 12019969, "bathrooms": 1.0, "bedrooms": 2, "beds": 4, "disc_m": 1.0, "disc_w": 0.86, "coordinates": {"lat": 50.09607, "lng": 14.46551}}, {"id": 29066488, "bathrooms": 1.0, "bedrooms": 2, "beds": 3, "disc_m": 1.0, "disc_w": 1.0, "coordinates": {"lat": 50.0978, "lng": 14.46404}}, {"id": 36975154, "bathrooms": 1.0, "bedrooms": 0, "beds": 2, "disc_m": 1.0, "disc_w": 0.9, "coordinates": {"lat": 50.1057, "lng": 14.46891}}, {"id": 15368023, "bathrooms": 1.0, "bedrooms": 2, "beds": 2, "disc_m": 0.67, "disc_w": 0.82, "coordinates": {"lat": 50.10507, "lng": 14.47419}}, {"id": 27646955, "bathrooms": 1.5, "bedrooms": 2, "beds": 2, "disc_m": 1.0, "disc_w": 1.0, "coordinates": {"lat": 50.09734, "lng": 14.467662}}, {"id": 16215240, "bathrooms": 1.0, "bedrooms": 2, "beds": 2, "disc_m": 1.0, "disc_w": 1.0, "coordinates": {"lat": 50.09589, "lng": 14.46421}}, {"id": 18011488, "bathrooms": 1.0, "bedrooms": 1, "beds": 2, "disc_m": 0.85, "disc_w": 0.9, "coordinates": {"lat": 50.10575, "lng": 14.47405}}, {"id": 19899155, "bathrooms": 1.0, "bedrooms": 2, "beds": 3, "disc_m": 1.0, "disc_w": 1.0, "coordinates": {"lat": 50.09607, "lng": 14.46594}}, {"id": 5100076, "bathrooms": 1.0, "bedrooms": 2, "beds": 4, "disc_m": 0.8, "disc_w": 0.9, "coordinates": {"lat": 50.096954, "lng": 14.465209}}, {"id": 5988109, "bathrooms": 1.5, "bedrooms": 1, "beds": 2, "disc_m": 1.0, "disc_w": 0.89, "coordinates": {"lat": 50.09781, "lng": 14.4641}}, {"id": 28452348, "bathrooms": 1.0, "bedrooms": 1, "beds": 2, "disc_m": 0.9, "disc_w": 0.9, "coordinates": {"lat": 50.105343, "lng": 14.470547}}, {"id": 16379465, "bathrooms": 1.0, "bedrooms": 1, "beds": 2, "disc_m": 0.85, "disc_w": 0.95, "coordinates": {"lat": 50.10347, "lng": 14.47165}}, {"id": 6184144, "bathrooms": 1.0, "bedrooms": 1, "beds": 2, "disc_m": 0.9, "disc_w": 1.0, "coordinates": {"lat": 50.10074, "lng": 14.47234}}, {"id": 22123894, "bathrooms": 1.0, "bedrooms": 1, "beds": 2, "disc_m": 0.86, "disc_w": 0.93, "coordinates": {"lat": 50.09672, "lng": 14.46766}}, {"id": 13593131, "bathrooms": 1.0, "bedrooms": 1, "beds": 1, "disc_m": 0.7, "disc_w": 0.9, "coordinates": {"lat": 50.09658, "lng": 14.46495}}, {"id": 9571502, "bathrooms": 1.0, "bedrooms": 1, "beds": 2, "disc_m": 1.0, "disc_w": 0.95, "coordinates": {"lat": 50.10688, "lng": 14.47496}}, {"id": 36836911, "bathrooms": 1.0, "bedrooms": 1, "beds": 1, "disc_m": 1.0, "disc_w": 1.0, "coordinates": {"lat": 50.10039, "lng": 14.46995}}, {"id": 3070237, "bathrooms": 1.0, "bedrooms": 2, "beds": 2, "disc_m": 0.85, "disc_w": 0.95, "coordinates": {"lat": 50.09624, "lng": 14.46558}}, {"id": 20703155, "bathrooms": 1.0, "bedrooms": 0, "beds": 2, "disc_m": 0.85, "disc_w": 0.9, "coordinates": {"lat": 50.104462, "lng": 14.47195}}, {"id": 21664430, "bathrooms": 1.0, "bedrooms": 0, "beds": 2, "disc_m": 0.7, "disc_w": 0.9, "coordinates": {"lat": 50.10682, "lng": 14.46562}}, {"id": 27693197, "bathrooms": 1.0, "bedrooms": 2, "beds": 2, "disc_m": 1.0, "disc_w": 1.0, "coordinates": {"lat": 50.1035, "lng": 14.4744}}, {"id": 4192947, "bathrooms": 1.0, "bedrooms": 0, "beds": 1, "disc_m": 0.73, "disc_w": 0.9, "coordinates": {"lat": 50.09577, "lng": 14.46403}}, {"id": 4281403, "bathrooms": 1.0, "bedrooms": 2, "beds": 5, "disc_m": 0.75, "disc_w": 0.9, "coordinates": {"lat": 50.09801, "lng": 14.46483}}, {"id": 14851186, "bathrooms": 1.0, "bedrooms": 1, "beds": 3, "disc_m": 1.0, "disc_w": 1.0, "coordinates": {"lat": 50.097973, "lng": 14.470808}}, {"id": 4043897, "bathrooms": 1.0, "bedrooms": 2, "beds": 5, "disc_m": 0.7, "disc_w": 0.9, "coordinates": {"lat": 50.09573, "lng": 14.46405}}, {"id": 4254908, "bathrooms": 1.0, "bedrooms": 2, "beds": 2, "disc_m": 0.7, "disc_w": 0.9, "coordinates": {"lat": 50.09787, "lng": 14.46461}}, {"id": 16223503, "bathrooms": 1.0, "bedrooms": 2, "beds": 2, "disc_m": 0.75, "disc_w": 0.9, "coordinates": {"lat": 50.09788, "lng": 14.46408}}, {"id": 10674592, "bathrooms": 1.0, "bedrooms": 2, "beds": 4, "disc_m": 0.56, "disc_w": 1.0, "coordinates": {"lat": 50.09723, "lng": 14.46494}}, {"id": 28456893, "bathrooms": 2.0, "bedrooms": 3, "beds": 6, "disc_m": 1.0, "disc_w": 1.0, "coordinates": {"lat": 50.10599, "lng": 14.46602}}, {"id": 21856055, "bathrooms": 1.0, "bedrooms": 2, "beds": 3, "disc_m": 0.85, "disc_w": 0.9, "coordinates": {"lat": 50.10494, "lng": 14.47311}}, {"id": 18860675, "bathrooms": 1.0, "bedrooms": 1, "beds": 4, "disc_m": 0.9, "disc_w": 1.0, "coordinates": {"lat": 50.10525, "lng": 14.47076}}, {"id": 9192997, "bathrooms": 1.0, "bedrooms": 1, "beds": 1, "disc_m": 0.85, "disc_w": 0.9, "coordinates": {"lat": 50.10361, "lng": 14.47411}}, {"id": 22281324, "bathrooms": 1.0, "bedrooms": 1, "beds": 1, "disc_m": 0.8, "disc_w": 1.0, "coordinates": {"lat": 50.10679, "lng": 14.47397}}, {"id": 9152832, "bathrooms": 1.0, "bedrooms": 1, "beds": 2, "disc_m": 0.85, "disc_w": 0.9, "coordinates": {"lat": 50.10207, "lng": 14.47467}}, {"id": 167878, "bathrooms": 1.0, "bedrooms": 2, "beds": 2, "disc_m": 1.0, "disc_w": 1.0, "coordinates": {"lat": 50.10495, "lng": 14.46924}}, {"id": 26969636, "bathrooms": 2.5, "bedrooms": 1, "beds": 1, "disc_m": 1.0, "disc_w": 1.0, "coordinates": {"lat": 50.03342, "lng": 14.52219}}, {"id": 15505133, "bathrooms": 1.0, "bedrooms": 1, "beds": 1, "disc_m": 0.6, "disc_w": 0.85, "coordinates": {"lat": 50.03521, "lng": 14.5333}}, {"id": 13608421, "bathrooms": 1.0, "bedrooms": 1, "beds": 2, "disc_m": 0.72, "disc_w": 0.9, "coordinates": {"lat": 50.03, "lng": 14.51772}}, {"id": 16111543, "bathrooms": 1.0, "bedrooms": 1, "beds": 1, "disc_m": 1.0, "disc_w": 0.97, "coordinates": {"lat": 50.02786, "lng": 14.52014}}, {"id": 14725935, "bathrooms": 1.5, "bedrooms": 2, "beds": 3, "disc_m": 0.9, "disc_w": 0.95, "coordinates": {"lat": 50.02727, "lng": 14.52985}}, {"id": 16513267, "bathrooms": 1.0, "bedrooms": 2, "beds": 5, "disc_m": 0.85, "disc_w": 0.9, "coordinates": {"lat": 50.034756, "lng": 14.5138}}, {"id": 35638796, "bathrooms": 1.0, "bedrooms": 1, "beds": 1, "disc_m": 1.0, "disc_w": 0.95, "coordinates": {"lat": 50.02615, "lng": 14.529}}, {"id": 342963, "bathrooms": 1.0, "bedrooms": 1, "beds": 5, "disc_m": 0.75, "disc_w": 0.85, "coordinates": {"lat": 50.05323, "lng": 14.53235}}, {"id": 34387023, "bathrooms": 1.0, "bedrooms": 1, "beds": 2, "disc_m": 1.0, "disc_w": 1.0, "coordinates": {"lat": 50.03107, "lng": 14.52941}}, {"id": 34188903, "bathrooms": 1.0, "bedrooms": 1, "beds": 1, "disc_m": 0.7, "disc_w": 0.9, "coordinates": {"lat": 50.01861, "lng": 14.51202}}, {"id": 24985683, "bathrooms": 1.5, "bedrooms": 3, "beds": 5, "disc_m": 0.85, "disc_w": 1.0, "coordinates": {"lat": 50.02696, "lng": 14.51862}}, {"id": 11900914, "bathrooms": 1.0, "bedrooms": 1, "beds": 1, "disc_m": 0.75, "disc_w": 0.92, "coordinates": {"lat": 50.02453, "lng": 14.52931}}, {"id": 22678088, "bathrooms": 1.0, "bedrooms": 1, "beds": 1, "disc_m": 0.87, "disc_w": 0.9, "coordinates": {"lat": 50.052361, "lng": 14.532255}}, {"id": 1735621, "bathrooms": 1.0, "bedrooms": 1, "beds": 2, "disc_m": 0.88, "disc_w": 0.94, "coordinates": {"lat": 50.05179, "lng": 14.51314}}, {"id": 34863335, "bathrooms": 1.0, "bedrooms": 1, "beds": 2, "disc_m": 1.0, "disc_w": 0.7, "coordinates": {"lat": 50.03034, "lng": 14.5275}}, {"id": 15071007, "bathrooms": 1.0, "bedrooms": 0, "beds": 2, "disc_m": 0.85, "disc_w": 0.95, "coordinates": {"lat": 50.044235, "lng": 14.516666}}, {"id": 29224091, "bathrooms": 1.0, "bedrooms": 1, "beds": 2, "disc_m": 1.0, "disc_w": 1.0, "coordinates": {"lat": 50.0529, "lng": 14.50998}}, {"id": 7061831, "bathrooms": 1.0, "bedrooms": 1, "beds": 2, "disc_m": 1.0, "disc_w": 0.86, "coordinates": {"lat": 50.033802, "lng": 14.524591}}, {"id": 23010761, "bathrooms": 1.0, "bedrooms": 0, "beds": 1, "disc_m": 0.9, "disc_w": 0.95, "coordinates": {"lat": 50.05272, "lng": 14.53395}}, {"id": 11716361, "bathrooms": 1.0, "bedrooms": 2, "beds": 2, "disc_m": 0.7, "disc_w": 0.85, "coordinates": {"lat": 50.043507, "lng": 14.516297}}, {"id": 9199929, "bathrooms": 1.0, "bedrooms": 1, "beds": 4, "disc_m": 0.9, "disc_w": 0.9, "coordinates": {"lat": 50.04489, "lng": 14.51381}}, {"id": 18283073, "bathrooms": 1.0, "bedrooms": 0, "beds": 2, "disc_m": 0.8, "disc_w": 0.9, "coordinates": {"lat": 50.05119, "lng": 14.53257}}, {"id": 13429320, "bathrooms": 1.0, "bedrooms": 1, "beds": 2, "disc_m": 0.67, "disc_w": 0.8, "coordinates": {"lat": 50.03414, "lng": 14.51519}}, {"id": 25485841, "bathrooms": 1.0, "bedrooms": 2, "beds": 6, "disc_m": 0.75, "disc_w": 0.9, "coordinates": {"lat": 50.05034, "lng": 14.5234}}, {"id": 8078176, "bathrooms": 1.0, "bedrooms": 2, "beds": 2, "disc_m": 0.9, "disc_w": 1.0, "coordinates": {"lat": 50.03025, "lng": 14.53233}}, {"id": 30543983, "bathrooms": 1.0, "bedrooms": 0, "beds": 2, "disc_m": 0.85, "disc_w": 0.95, "coordinates": {"lat": 50.052361, "lng": 14.532255}}, {"id": 24973023, "bathrooms": 1.0, "bedrooms": 1, "beds": 2, "disc_m": 0.8, "disc_w": 0.95, "coordinates": {"lat": 50.052227, "lng": 14.531849}}, {"id": 31096874, "bathrooms": 2.0, "bedrooms": 1, "beds": 2, "disc_m": 1.0, "disc_w": 1.0, "coordinates": {"lat": 50.04883, "lng": 14.53402}}, {"id": 31018712, "bathrooms": 1.0, "bedrooms": 1, "beds": 4, "disc_m": 1.0, "disc_w": 1.0, "coordinates": {"lat": 50.052, "lng": 14.51526}}, {"id": 13080425, "bathrooms": 1.0, "bedrooms": 2, "beds": 2, "disc_m": 1.0, "disc_w": 0.9, "coordinates": {"lat": 50.053299, "lng": 14.514127}}, {"id": 13013847, "bathrooms": 1.0, "bedrooms": 1, "beds": 1, "disc_m": 0.67, "disc_w": 0.8, "coordinates": {"lat": 50.03334, "lng": 14.51464}}, {"id": 28502702, "bathrooms": 1.0, "bedrooms": 0, "beds": 3, "disc_m": 0.95, "disc_w": 1.0, "coordinates": {"lat": 50.02694, "lng": 14.52359}}, {"id": 13100762, "bathrooms": 1.5, "bedrooms": 1, "beds": 2, "disc_m": 0.9, "disc_w": 0.97, "coordinates": {"lat": 50.02006, "lng": 14.52353}}, {"id": 14752992, "bathrooms": 1.0, "bedrooms": 2, "beds": 5, "disc_m": 0.37, "disc_w": 0.64, "coordinates": {"lat": 50.04484, "lng": 14.51718}}, {"id": 35927907, "bathrooms": 1.0, "bedrooms": 1, "beds": 1, "disc_m": 1.0, "disc_w": 1.0, "coordinates": {"lat": 50.0517, "lng": 14.5308}}, {"id": 18404383, "bathrooms": 1.0, "bedrooms": 0, "beds": 1, "disc_m": 0.7, "disc_w": 1.0, "coordinates": {"lat": 50.05176, "lng": 14.53215}}, {"id": 16399553, "bathrooms": 1.0, "bedrooms": 2, "beds": 2, "disc_m": 1.0, "disc_w": 1.0, "coordinates": {"lat": 50.03804, "lng": 14.51323}}, {"id": 35461127, "bathrooms": 1.0, "bedrooms": 1, "beds": 1, "disc_m": 1.0, "disc_w": 1.0, "coordinates": {"lat": 50.02691, "lng": 14.51653}}, {"id": 5372697, "bathrooms": 2.0, "bedrooms": 3, "beds": 6, "disc_m": 1.0, "disc_w": 0.825481, "coordinates": {"lat": 50.02546, "lng": 14.53082}}, {"id": 23417623, "bathrooms": 2.5, "bedrooms": 1, "beds": 2, "disc_m": 0.95, "disc_w": 0.97, "coordinates": {"lat": 50.04081, "lng": 14.42122}}, {"id": 21777918, "bathrooms": 2.5, "bedrooms": 1, "beds": 2, "disc_m": 0.95, "disc_w": 0.97, "coordinates": {"lat": 50.04177, "lng": 14.42263}}, {"id": 15517250, "bathrooms": 1.0, "bedrooms": 1, "beds": 2, "disc_m": 0.51, "disc_w": 0.79, "coordinates": {"lat": 50.04095, "lng": 14.42558}}, {"id": 22993632, "bathrooms": 2.5, "bedrooms": 1, "beds": 1, "disc_m": 0.95, "disc_w": 0.97, "coordinates": {"lat": 50.04125, "lng": 14.42103}}, {"id": 14941852, "bathrooms": 1.5, "bedrooms": 1, "beds": 1, "disc_m": 1.0, "disc_w": 0.95, "coordinates": {"lat": 50.042805, "lng": 14.432668}}, {"id": 24403339, "bathrooms": 1.0, "bedrooms": 1, "beds": 3, "disc_m": 1.0, "disc_w": 1.0, "coordinates": {"lat": 50.04228, "lng": 14.42472}}, {"id": 24415696, "bathrooms": 1.0, "bedrooms": 1, "beds": 2, "disc_m": 1.0, "disc_w": 1.0, "coordinates": {"lat": 50.04186, "lng": 14.42427}}, {"id": 24415425, "bathrooms": 1.0, "bedrooms": 2, "beds": 4, "disc_m": 1.0, "disc_w": 1.0, "coordinates": {"lat": 50.04314, "lng": 14.42444}}, {"id": 24017592, "bathrooms": 1.0, "bedrooms": 0, "beds": 3, "disc_m": 1.0, "disc_w": 1.0, "coordinates": {"lat": 50.042, "lng": 14.42452}}, {"id": 36131624, "bathrooms": 1.0, "bedrooms": 3, "beds": 4, "disc_m": 1.0, "disc_w": 1.0, "coordinates": {"lat": 50.03786, "lng": 14.42482}}, {"id": 24010787, "bathrooms": 1.0, "bedrooms": 2, "beds": 5, "disc_m": 1.0, "disc_w": 1.0, "coordinates": {"lat": 50.04217, "lng": 14.42637}}, {"id": 27949344, "bathrooms": 1.0, "bedrooms": 1, "beds": 4, "disc_m": 1.0, "disc_w": 1.0, "coordinates": {"lat": 50.039646, "lng": 14.420678}}, {"id": 1922097, "bathrooms": 1.0, "bedrooms": 1, "beds": 1, "disc_m": 0.88, "disc_w": 0.94, "coordinates": {"lat": 50.04411, "lng": 14.42453}}, {"id": 22272336, "bathrooms": 1.0, "bedrooms": 2, "beds": 5, "disc_m": 1.0, "disc_w": 0.78, "coordinates": {"lat": 50.04208, "lng": 14.42573}}, {"id": 20278374, "bathrooms": 1.0, "bedrooms": 1, "beds": 5, "disc_m": 1.0, "disc_w": 1.0, "coordinates": {"lat": 50.03374, "lng": 14.42018}}, {"id": 35637591, "bathrooms": 1.5, "bedrooms": 1, "beds": 2, "disc_m": 1.0, "disc_w": 1.0, "coordinates": {"lat": 50.04286, "lng": 14.43265}}, {"id": 22272536, "bathrooms": 1.0, "bedrooms": 1, "beds": 3, "disc_m": 1.0, "disc_w": 1.0, "coordinates": {"lat": 50.04216, "lng": 14.42454}}, {"id": 22839740, "bathrooms": 2.5, "bedrooms": 1, "beds": 3, "disc_m": 0.95, "disc_w": 0.97, "coordinates": {"lat": 50.04195, "lng": 14.42109}}, {"id": 27744085, "bathrooms": 2.5, "bedrooms": 1, "beds": 2, "disc_m": 0.95, "disc_w": 0.97, "coordinates": {"lat": 50.04223, "lng": 14.42082}}, {"id": 29150050, "bathrooms": 2.5, "bedrooms": 1, "beds": 1, "disc_m": 0.95, "disc_w": 0.97, "coordinates": {"lat": 50.04043, "lng": 14.42048}}, {"id": 23203532, "bathrooms": 1.0, "bedrooms": 1, "beds": 10, "disc_m": 1.0, "disc_w": 1.0, "coordinates": {"lat": 50.03446, "lng": 14.42019}}, {"id": 31048535, "bathrooms": 1.0, "bedrooms": 2, "beds": 1, "disc_m": 0.55, "disc_w": 0.85, "coordinates": {"lat": 50.03503, "lng": 14.42212}}]